freesia/__init__.py
freesia-3.3.3.dist-info/LICENSE
freesia-3.3.3.dist-info/METADATA
freesia-3.3.3.dist-info/WHEEL
freesia-3.3.3.dist-info/top_level.txt
freesia-3.3.3.dist-info/RECORD
