Metadata-Version: 2.1
Name: freesia
Version: 3.3.3
Summary: Takes Qt for Python and adds extra functionality including automatic scaling
Home-page: https://gitlab.com/lgwilliams/freesia.git
Author: Luke Williams
Author-email: luke@dominoid.net
License: LGPL v2.1
Platform: UNKNOWN
Classifier: Programming Language :: Python :: 3
Classifier: Programming Language :: Python :: 3.7
Requires-Dist: PySide2
